sqlite3_prompt/__init__.py
sqlite3_prompt/helpers_config.py
sqlite3_prompt/i18n.py
sqlite3_prompt/main.py
sqlite3_prompt/locales/en/LC_MESSAGES/messages.mo
sqlite3_prompt-0.0.3.dist-info/licenses/LICENSE
sqlite3_prompt-0.0.3.dist-info/METADATA
sqlite3_prompt-0.0.3.dist-info/WHEEL
sqlite3_prompt-0.0.3.dist-info/entry_points.txt
sqlite3_prompt-0.0.3.dist-info/top_level.txt
sqlite3_prompt-0.0.3.dist-info/RECORD
