Metadata-Version: 2.4
Name: sqlite3-prompt
Version: 0.0.3
Summary: 一个功能强大的、支持自动补全和语法高亮的SQLite3命令行终端。
Author-email: "jk.zhou" <1406584456@qq.com>
License: Copyright © 2025 jk.zhou
Classifier: Programming Language :: Python :: 3
Classifier: License :: OSI Approved :: MIT License
Classifier: Operating System :: OS Independent
Classifier: Topic :: Database
Classifier: Topic :: Terminals
Classifier: Environment :: Console
Requires-Python: >=3.8
License-File: LICENSE
Requires-Dist: prompt-toolkit
Requires-Dist: Pygments
Requires-Dist: tabulate
Requires-Dist: platformdirs
Dynamic: license-file
